lotterycn/__init__.py
lotterycn/data.py
lotterycn/test.py
lotterycn-0.0.4.dist-info/LICENSE
lotterycn-0.0.4.dist-info/METADATA
lotterycn-0.0.4.dist-info/WHEEL
lotterycn-0.0.4.dist-info/top_level.txt
lotterycn-0.0.4.dist-info/RECORD
