Metadata-Version: 2.1
Name: lotterycn
Version: 0.0.4
Summary: LotteryCN is a library which aims to bring enjoyable analysis of lottery in Python
Home-page: https://github.com/uliontse/lotterycn
Author: UlionTse
Author-email: shinalone@outlook.com
License: MIT
Project-URL: Source, https://github.com/UlionTse/lotterycn
Project-URL: Changelog, https://github.com/UlionTse/lotterycn/blob/master/change_log.txt
Project-URL: Documentation, https://github.com/UlionTse/lotterycn/blob/master/README.md
Keywords: lottery
Classifier: Development Status :: 5 - Production/Stable
Classifier: Environment :: Web Environment
Classifier: Intended Audience :: Developers
Classifier: License :: OSI Approved :: MIT License
Classifier: Programming Language :: Python :: 3 :: Only
Classifier: Programming Language :: Python :: 3.6
Classifier: Programming Language :: Python :: 3.7
Classifier: Programming Language :: Python :: 3.8
Classifier: Programming Language :: Python :: 3.9
Classifier: Programming Language :: Python :: 3.10
Classifier: Programming Language :: Python :: 3.11
Requires-Python: >=3.6
License-File: LICENSE
Requires-Dist: tqdm (>=4.64.1)
Requires-Dist: numpy (>=1.21.6)
Requires-Dist: pandas (>=1.4.0)
Requires-Dist: requests (>=2.28.1)
Provides-Extra: pypi
Requires-Dist: build (>=0.8.0) ; extra == 'pypi'
Requires-Dist: twine (>=4.0.1) ; extra == 'pypi'
